amsdal_utils/Third-Party Materials - AMSDAL Dependencies - License Notices.md
amsdal_utils/__about__.py
amsdal_utils/__init__.py
amsdal_utils/errors.py
amsdal_utils/py.typed
amsdal_utils/classes/__init__.py
amsdal_utils/classes/metadata_manager.py
amsdal_utils/classes/transaction_manager.py
amsdal_utils/classes/version_manager.py
amsdal_utils/config/__init__.py
amsdal_utils/config/enums.py
amsdal_utils/config/manager.py
amsdal_utils/config/data_models/__init__.py
amsdal_utils/config/data_models/amsdal_config.py
amsdal_utils/config/data_models/connection_config.py
amsdal_utils/config/data_models/integration_config.py
amsdal_utils/config/data_models/repository_config.py
amsdal_utils/config/data_models/resources_config.py
amsdal_utils/lifecycle/__init__.py
amsdal_utils/lifecycle/consumer.py
amsdal_utils/lifecycle/enum.py
amsdal_utils/lifecycle/producer.py
amsdal_utils/models/__init__.py
amsdal_utils/models/base.py
amsdal_utils/models/enums.py
amsdal_utils/models/data_models/__init__.py
amsdal_utils/models/data_models/address.py
amsdal_utils/models/data_models/core.py
amsdal_utils/models/data_models/enums.py
amsdal_utils/models/data_models/metadata.py
amsdal_utils/models/data_models/reference.py
amsdal_utils/models/data_models/table_schema.py
amsdal_utils/models/data_models/transaction.py
amsdal_utils/models/mixins/__init__.py
amsdal_utils/models/mixins/cached_mixin.py
amsdal_utils/models/utils/__init__.py
amsdal_utils/models/utils/get_subclasses.py
amsdal_utils/models/utils/reference_builders.py
amsdal_utils/query/__init__.py
amsdal_utils/query/enums.py
amsdal_utils/query/mixin.py
amsdal_utils/query/pull_out_filter.py
amsdal_utils/query/split.py
amsdal_utils/query/utils.py
amsdal_utils/query/data_models/__init__.py
amsdal_utils/query/data_models/filter.py
amsdal_utils/query/data_models/order_by.py
amsdal_utils/query/data_models/paginator.py
amsdal_utils/query/data_models/query_specifier.py
amsdal_utils/schemas/__init__.py
amsdal_utils/schemas/interfaces.py
amsdal_utils-0.5.8.dist-info/METADATA
amsdal_utils-0.5.8.dist-info/WHEEL
amsdal_utils-0.5.8.dist-info/licenses/LICENSE.txt
amsdal_utils-0.5.8.dist-info/RECORD
