Metadata-Version: 2.4
Name: amsdal_utils
Version: 0.5.8
Summary: Utils for AMSDAL data framework
Project-URL: Documentation, https://pypi.org/project/amsdal_utils/#readme
Project-URL: Issues, https://pypi.org/project/amsdal_utils/#issues
Project-URL: Source, https://pypi.org/project/amsdal_utils/
Author-email: "A. Michael Salem" <ams@amsdal.com>
License: AMSDAL End User License Agreement
License-File: LICENSE.txt
Classifier: Development Status :: 4 - Beta
Classifier: Programming Language :: Python
Classifier: Programming Language :: Python :: 3.11
Classifier: Programming Language :: Python :: 3.12
Classifier: Programming Language :: Python :: 3.13
Classifier: Programming Language :: Python :: Implementation :: CPython
Classifier: Programming Language :: Python :: Implementation :: PyPy
Requires-Python: <3.14,>=3.11
Requires-Dist: pydantic~=2.12
Requires-Dist: pyyaml~=6.0
